svpy/__init__.py
svpy/main.py
svpy-0.1.dist-info/METADATA
svpy-0.1.dist-info/WHEEL
svpy-0.1.dist-info/top_level.txt
svpy-0.1.dist-info/RECORD
